{
    "types": [
        "transition"
    ],
    "date": 1658771314,
    "title": "",
    "headline": "GTAµOnline",
    "subtitle": "BOOM IMMOBILIER",
    "content": "Qu'y a-t-il de mieux qu'un bon investissementµ? Le ronronnement de 20µmoteurs dans le garage de votre bon investissement. Le fait de pouvoir posséder 10µpropriétés signifie que vous pourrez ajouter jusqu'à 20µvéhicules à votre collection.",
    "url": "",
    "image": {
        "path": "sc/news/a0c69b6754aa423683ca6fd8/262272_GTAO_CE_Hot_Property_BF.dds",
        "filesize": 262272
    }
}