{"types":["transition"],"date":1644525917,"title":"","headline":"GTA Online","subtitle":"No pódio esta semana: BF Club rosa","content":"Nada faz o coração disparar como o som de fichas batendo e o cheiro de derrota. Visite o lobby do Cassino e Resort Diamond para tentar a sorte na Roda da Fortuna do GTA Online e sair com GTA$, roupas, acessórios e lanches, além de diversos prêmios misteriosos. <br /><br />O grande prêmio esta semana são as chaves do BF Club rosa exposto no pódio.<br />","url":"","image":{"path":"sc/news/57480d6565bb44da95782b77/349672_podium_wheel1.dds","filesize":349672}}