{"types":["transition"],"date":1532455282,"title":"","headline":"GTA Online","subtitle":"After Hours","content":"Los Santos es una ciudad de luces brillantes, noches largas y dinero sucio, especialmente en After Hours. Dirige el club nocturno más exclusivo de la ciudad, atrae a los mejores DJ y úsalo de tapadera para ocultar la red de organizaciones criminales más densa que jamás ha existido en San Andreas.<br />","url":"","image":{"path":"sc/news/AH_After_Hours/349672_Big_Feed_After_Hours.dds","filesize":349672},"style":"gta"}