{
    "types": [
        "transition"
    ],
    "date": 1759489335,
    "title": "GTA Online",
    "headline": "GTA Online",
    "subtitle": "Halloween va hanter Los Santos",
    "content": "Halloween envahit le sud de San Andreas durant tout le mois d'octobre pour répandre le chaos. Il y a des rumeurs d'ovnis, de métamorphoses étranges, et de bien plus encore dans GTAµOnline.<br /><br />Et célébrez la fête de la mi-automne dans GTAµOnline. Jouez à tout moment d'ici le 8µoctobre pour recevoir la casquette d'automne Yeti rouge, et que votre avenir soit aussi radieux qu'une pleine lune sur Los Santos. ",
    "url": "",
    "image": {
        "path": "sc/news/8e00691c95f54b66a1b8e00e/262272_GTAO_474_Lead_HalloweenHaunts_FINAL_BigFeed_R03_Deliv.dds",
        "filesize": 262272
    }
}