{"types":["transition"],"date":1617898540,"title":"","headline":"GTA Online","subtitle":"Promotions","content":"Profitez d'autres offres cette semaine, dont -40µ% sur tous les appartements de luxe, -50µ% sur les transformations en armes MkµII et des promotions sur divers véhiculesµ:<br /><br />• -30µ% sur la Grotti Cheetah classique<br />• -30µ% sur la Vapid Winky<br />• -40µ% sur le HVY Insurgent<br />• -40µ% sur la Lampadati Casco<br /><br />Et plusµ! Plus d'informations sur le Rockstar Newswire.","url":"","image":{"path":"sc/news/75bc35f5062e4f41adf5bd02/262272_Grotti_Cheetah_Classic.dds","filesize":262272}}