{"types":["transition"],"date":1629998011,"title":"","headline":"GTA Online","subtitle":"Fai un giro su auto nuove e in anteprima nell'area di prova","content":"Non c'è niente di male nel provare la taglia di qualcosa prima di comprarla. Lo fai con i pantaloni da Binco, quindi perché non dovresti farlo con un'auto? Passa nell'area di prova dell'Autoraduno di LS e scalda il motore della nuova Karin Sultan RS Classic, dell'inedita Übermacht Cypher e della Obey Tailgater S senza alcun costo, anche se graffi la vernice durante una Prova a tempo o una Corsa ai checkpoint.","url":"","image":{"path":"sc/news/a041f1a4278b40458c1dfe54/262272_GTA0263_Test_Ride_FINAL_DRAFT_BigFeed_V2.dds","filesize":262272}}