{
    "types": [
        "transition"
    ],
    "date": 1644525913,
    "title": "",
    "headline": "GTA Online",
    "subtitle": "Pojazd do wygrania w tym tygodniu: Albany Roosevelt",
    "content": "A może jedyną miłością twojego życia jest trasa. W takim razie członkowie klubu samochodowego LS, którzy wygrają serię wyścigów ulicznych przez trzy dni z rzędu, otrzymają kluczyki do Albany Roosevelta, który zaprezentowany jest na Slamtrucku w samym sercu klubu. Ta historyczna limuzyna jest tak klasyczna i ponadczasowa, że nadaje się do muzeum.",
    "url": "",
    "image": {
        "path": "sc/news/3cccaa0970f04987848db858/262272_GTAO286_PrizeRide_FINAL_BigFeed.dds",
        "filesize": 262272
    }
}