{
    "types": [
        "transition"
    ],
    "date": 1636717753,
    "title": "",
    "headline": "GTA Online",
    "subtitle": "Schalte das Atomic-Motorsport-Design frei",
    "content": "Wenn du ein beliebiges der drei Doomsday-Heist-Finale abschließt, wirst du mit dem Atomic-Motorsport-Design für den Sultan RS Classic belohnt (innerhalb von 72 Stunden nach einem Login nach dem 22. November).<br /><br />Wenn du alle drei Finale abschließt, erhältst du zusätzlich 500.000 GTA$, die deinem Maze-Bank-Konto bis zum 21. November gutgeschrieben werden.",
    "url": "",
    "image": {
        "path": "sc/news/5475d6c67dc24d27854825b9/262272_GTAO274_AtomicLivery_FINAL_BigFeed.dds",
        "filesize": 262272
    }
}