{
    "types": [
        "transition"
    ],
    "date": 1636717753,
    "title": "",
    "headline": "GTA Online",
    "subtitle": "Sblocca la livrea Atomic Motorsport",
    "content": "Completando qualsiasi dei tre colpi conclusivi de Il colpo dell’apocalisse ti assicurerai la livrea Atomic Motorsport per la Sultan RS Classic, che riceverai entro 72 ore dall’accesso dopo il 22 novembre.<br /><br />Inoltre, completando tutti e tre i colpi conclusivi de Il colpo dell’apocalisse riceverai 500.000 GTA$ extra, che verranno depositati sul tuo conto di gioco presso la Maze Bank entro il 21 novembre.",
    "url": "",
    "image": {
        "path": "sc/news/5475d6c67dc24d27854825b9/262272_GTAO274_AtomicLivery_FINAL_BigFeed.dds",
        "filesize": 262272
    }
}