{"types":["transition"],"date":1679592332,"title":"","headline":"GTA Online","subtitle":"GTA$ et RP doublés dans toutes les missions narratives de Los Santos Drug Wars","content":"Plongez dans les tréfonds du marché noir médical du sud de San Andreas pour aider Dax et les Fooliganz dans toutes les missions narratives de la Première dose et de la Dernière dose, et profitez de GTA$ et RP doublés.","url":"","image":{"path":"sc/news/addbb066f32f4f268dc95619/262272_GTAO342_LSDW_Bonuses_FINAL_BigFeed.dds","filesize":262272}}