{
    "types": [
        "transition"
    ],
    "date": 1728640356,
    "title": "GTAオンライン",
    "headline": "GTAオンライン",
    "subtitle": "ノース・ヤンクトンの悪夢のコミュニティチャレンジ",
    "content": "今回は「GTAオンライン」のコミュニティへチャレンジが課されます。ルーデンドルフの町をアンデッドの大群から守ってください。新しい「ルーデンドルフ墓地サバイバル」において、コミュニティの皆さんで合計8,000万のゾンビを倒せば、オレンジの発光スケルトンワンジーと赤のフード付きスカルマスクを獲得できます。",
    "url": "",
    "image": {
        "path": "sc/news/65fc9e38df55493a8c1d81e6/262272_GTAO_421_LCS_CommunityChallenge_FINAL_BigFeed_R02_V1.dds",
        "filesize": 262272
    }
}