{
    "types": [
        "transition"
    ],
    "date": 1631210242,
    "title": "",
    "headline": "GTA Online",
    "subtitle": "2x Reputação em todas as atividades do Evento de Carros",
    "content": "Membros que participarem de qualquer atividade do Evento de Carros LS vão receber o dobro de Reputação, inclusive ao modificar veículos na Loja de Modificações do Evento, disputar Disparadas, Correrias, Corridas de Rua em Série ou a Perseguição em Série.",
    "url": "",
    "image": {
        "path": "sc/news/51f074c646e743399a9f133a/262272_GTA265_Car_Meetup_Bonuses_FINAL_BigFeed.dds",
        "filesize": 262272
    }
}