{"types":["transition"],"date":1475515629,"title":"","headline":"GTA Online","subtitle":"Un nid douillet","content":"Au départ, le QG de votre club de motards ressemblera peut-être à un trou à rats désaffecté, mais ça ne durera pas longtemps. Vous pourrez y apposer votre touche personnelle, de l'ajout d'une fresque murale jusqu'à l'installation d'un véritable atelier de tuning pour vos motos. Votre clique pourra venir se détendre au QG à tout moment. De plus, c'est ici que vous mettrez au point vos missions de club de motards et que vous pourrez vous lancer dans les affaires.","url":"","image":{"path":"sc/news/NG_Bikers_HomeIsYourCastle/262272_MazeForeclosure.dds","filesize":262272},"landscape":{"path":"sc/news/NG_Bikers_HomeIsYourCastle/.dds","filesize":2048}}