{
    "types": [
        "transition"
    ],
    "date": 1626362456,
    "title": "",
    "headline": "GTA 온라인",
    "subtitle": "로스 산토스 튜너 7월 20일 출시",
    "content": "7월 20일 GTA 온라인: 로스 산토스 튜너 출시와 함께 암암리에 펼쳐지던 자동차 집회가 급부상해 자리매김하게 됩니다.<br /><br />이번 업데이트에서는 액션 가득한 튜너 기반 임무와 레이스를 제공합니다. 이번에 추가되는 새 모임 활동인 LS 자동차 모임에서 동료 자동차광들과 함께 자유로이 레이스를 즐기며, 자신만의 개조 이동 수단을 뽐내 보세요. 그리고 뛰어난 실력의 드라이버를 구하는 연락책들과 인맥을 쌓을 수 있는 절호의 기회 또한 제공됩니다.",
    "url": "",
    "image": {
        "path": "sc/news/686b8170008d4fcbb682b936/262272_GTAO_Tuners_FINAL_BigFeed.dds",
        "filesize": 262272
    }
}