{
    "types": [
        "transition"
    ],
    "date": 1680182575,
    "title": "",
    "headline": "GTA Online",
    "subtitle": "Questa settimana i centauri dominano la strada mentre gli affari s'impennano",
    "content": "Vai su The Open Road in GTA Online e goditi i bonus di Centauri.<br /><br />• GTA$/RP doppi nelle missioni di vendita di Centauri<br />• Velocità di produzione degli stabilimenti di Centauri raddoppiata<br />• Scorte doppie nelle missioni di vendita degli stabilimenti di Centauri<br />• GTA$ e RP doppi in Incarichi e Sfide dell’MC e nelle Commissioni della clubhouse.<br /><br />Se devi entrare nel giro dei club motociclistici illegali di Southern San Andreas procurati una clubhouse da Maze Bank Foreclosures con il -40%.",
    "url": "",
    "image": {
        "path": "sc/news/2928247e3bc5441b871efb41/262272_GTAO_343_Lead_BikerBonuses_FINAL_BigFeed.dds",
        "filesize": 262272
    }
}