{
    "types": [
        "transition"
    ],
    "date": 1630603106,
    "title": "",
    "headline": "GTAµOnline",
    "subtitle": "GTA$ et RP doublés dans les missions de DJ",
    "content": "Les DJ sont souvent très exigeants. Et justement, Tom Connors a besoin d'aide pour répondre aux moindres désirs des superstars de The Music Locker. Si vous recevez un message de sa part, n'oubliez pas que les missions de DJ octroient le double de GTA$ et de RP.",
    "url": "",
    "image": {
        "path": "sc/news/5c6bad4b4aa84d55a9bc592b/262272_GTAO264_DJRequestMissions_FINAL_BigFeed.dds",
        "filesize": 262272
    }
}