{
    "types": [
        "standalone"
    ],
    "date": 1774539338,
    "title": "GTA+",
    "headline": "GTA+",
    "subtitle": "Tritt GTA+ bei, um Vorteile zu erhalten",
    "content": "Abonniere das Premium-Mitgliedschaftsprogramm von GTAµOnline und erhalte monatliche Vorteile wie 500.000µGTA$µ& mehr. Mitglieder bei GTA+ erhalten bis 1.µApril:<br /><br />– den Vapid Firebolt ASP (Geländewagen)<br />– 50µ% Rabatt auf Schrotthandel sowie ihre Verbesserungen und Anpassungen<br />– 2xµGTA$ an täglichen Einnahmen beim Schrotthandel<br />– das Broker-Prolaps-Basketballtrikot und die -shorts<br />– und mehr<br /><br />Die Mitgliedschaft verlängert sich monatlich und ist jederzeit kündbar. Mehr auf rsg.ms/gtaplus.",
    "url": "class=uiGoToPageMessage target=store_plus",
    "image": {
        "path": "sc/news/17ce344ca14f467e97000c5f/262272_GTAPlus_MEP49_Lead_VapidFireboltASP_FINAL_BigFeed_R05_de_de_Deliv.dds",
        "filesize": 262272
    }
}