{
    "types": [
        "standalone"
    ],
    "date": 1774539338,
    "title": "GTA+",
    "headline": "GTA+",
    "subtitle": "Оформите подписку GTA+ и получите бонусы",
    "content": "Оформите подписку GTA+, чтобы каждый месяц получать эксклюзивные бонусы, в том числе 500 000 GTA $ и не только. До 1 апреля подписчикам доступны:<br /><br />- Vapid Firebolt ASP (вездеход)<br />- скидка 50% на утилизационные цеха, а также улучшения и модификации для них<br />- 2X GTA $ за работу утилизационного цеха<br />- баскетбольные шорты и футболка Broker Prolaps<br />- и не только<br /><br />Подписка обновляется автоматически каждый месяц; вы можете отменить ее в любое время. Подробности – на сайте rsg.ms/gtaplus.",
    "url": "class=uiGoToPageMessage target=store_plus",
    "image": {
        "path": "sc/news/17ce344ca14f467e97000c5f/262272_GTAPlus_MEP49_Lead_VapidFireboltASP_FINAL_BigFeed_R05_ru_ru_Deliv.dds",
        "filesize": 262272
    }
}