{
    "types": [
        "transition"
    ],
    "date": 1717151507,
    "title": "GTA Online",
    "headline": "GTA Online",
    "subtitle": "3X GTA $ и RP за задания клиентов в Terrorbyte",
    "content": "Benefactor славится своими передовыми технологиями, а Terrorbyte, помимо прочего, также позволит вам завязать контакт с гениальной хакершей Пейдж Харрис. Запускайте задания клиентов Terrorbyte из центра управления и помогайте останавливать различные преступления по всему городу за тройные GTA $ и RP.<br /><br />Завершив три задания клиентов в Terrorbyte, вы выполните условия текущего еженедельного испытания, за которое получите 100 000 GTA $.",
    "url": "",
    "image": {
        "path": "sc/news/6ae26d875e5a4ca18b8c4be8/262272_GTAO296_Terrorbyte_Client_FINAL_BigFeed.dds",
        "filesize": 262272
    }
}