{
    "types": [
        "transition"
    ],
    "date": 1772207529,
    "title": "GTA Online",
    "headline": "GTA Online",
    "subtitle": "Zdobądź nowego Shitzu Keitorę",
    "content": "W przeciwieństwie do przynudzających influencerów na Bleeterze i LifeInvaderze, Shitzu Keitora w pełni zasłużył na grono wielbicieli. Nie daj się oszukać jego małym rozmiarom – ten importowany samochód użytkowy zawstydza mocą inne auta swojej klasy, dorabiając po godzinach na torze driftowym.<br /><br />Dołącz do jego fanów i dorwij nową Keitorę w salonie Southern San Andreas Super Autos. Możesz ją też przetestować za darmo na torze klubu samochodowego LS.",
    "url": "",
    "image": {
        "path": "sc/news/a584b4e227d94a65aedd58e7/262272_GTAO_488_ShitzuKeitora_FINAL_BigFeed_Deliv.dds",
        "filesize": 262272
    }
}