{
    "types": [
        "priority"
    ],
    "date": 1749650431,
    "title": "GTAオンライン：マネーフロント",
    "headline": "GTAオンライン：マネーフロント",
    "subtitle": "6月17日登場",
    "content": "サンアンドレアス最大のマネーロンダリング事業を運営しましょう。「GTAオンライン」の最新アップデート「マネーフロント」が6月17日に登場します。<br /><br />地元の名物事業を買収し、複雑に入り組んだマネーロンダリング事業を利用して、自身の犯罪帝国を発展させましょう。",
    "url": "",
    "image": {
        "path": "sc/news/7145c6b6bae64e5181b25d01/262272_GTAO_455_TUAnnounce_HandsOnCarWashProprty_FINAL_BigFeed_V1_Deliv.dds",
        "filesize": 262272
    }
}