{"types":["transition"],"date":1623346061,"title":"","headline":"GTA Online","subtitle":"Bonificaciones de Importación/Exportación en GTA Online","content":"Tanto trabajo mangando vehículos está a punto de dar sus frutos. Completa con éxito cualquier misión de venta de vehículos hasta el 23 de junio, y obtén el doble de GTA$ y RP.<br /><br />Además, si robas cinco o más vehículos completando varias misiones de robo de vehículos durante las próximas dos semanas, recibirás un bonus de 250µ000µGTA$. Si te pones las pilas y traes diez o más, recibirás medio millón de GTA$. Estas bonificaciones se ingresarán en tu cuenta del Maze Bank antes del 30 de junio.","url":"","image":{"path":"sc/news/49503331bf864fdab841f9f3/262272_GTAO253_ImportExport_Lead_asset_FINAL_BigFeed_Logo.dds","filesize":262272}}