{"types":["transition"],"date":1513097119,"title":"","headline":"GTA Online","subtitle":"Zemsta jest słodka","content":"Latająca forteca, powietrzne laboratorium kryminalistyczne, morderczy dewastator otoczenia: Avenger to wszystko to i jeszcze trochę – kompleksowe rozwiązanie dla kryminalisty szukającego najbardziej przerażającego obiektu, jaki kiedykolwiek wzniósł się w powietrze. Przechowuj go w swojej bazie, rozbuduj o warsztat pojazdów, warsztat zbrojeniowy i cały zestaw przerażającego uzbrojenia, a już wkrótce zasiejesz zniszczenie, jakiego świat pod Tobą jeszcze nie zaznał. ","url":"","image":{"path":"sc/news/DH_Vengeance_Is_Sweet/262272_plane_1.dds","filesize":262272},"style":"gta"}