{
    "types": [
        "standalone"
    ],
    "date": 1757616866,
    "title": "Grand Theft Auto: Vice City - The Definitive Edition (Dispositivos móveis)",
    "headline": "Grand Theft Auto: Vice City - The Definitive Edition (Dispositivos móveis)",
    "subtitle": "Escaneie o código QR para baixar",
    "content": "Boas-vindas aos anos 80. Da década de penteados glam e dos ternos pastel, vem a história de um homem que sobe ao topo da cadeia criminal.<br /><br />Escaneie o código QR para aprender a jogar Grand Theft Auto: Vice City - The Definitive Edition no seu dispositivo móvel de graça como parte da sua Afiliação GTA+.",
    "url": "",
    "image": {
        "path": "sc/news/25d487fc8f28433196893946/262272_GTAPlus_MP43_GTAViceCityDefinitiveEdition_FINAL_BigFeed_Deliv.dds",
        "filesize": 262272
    }
}