{"types":["transition"],"date":1563898496,"title":"","headline":"GTA Online","subtitle":"ÚNETE AL CLUB","content":"Apreciamos a todos nuestros clientes, pero algunos son más valiosos que otros.<br /><br />Hazte socio de The Diamond Casino & Resort y disfrutarás del prestigio social que solo el dinero puede comprar. Recibe una bienvenida insuperable, llena de ventajas, beneficios, bonificaciones, privilegios, palmaditas en la espalda, guiños, servidumbre y adulación.<br /><br />Tú ya estás por encima del resto. Solo queremos hacerlo oficial.","url":"","image":{"path":"sc/news/a8544fb46a8346a6abde8e0b/349672_Diamond_Casino_JOIN_THE_CLUB.dds","filesize":349672}}