{
    "types": [
        "transition"
    ],
    "date": 1726153047,
    "title": "GTA Online",
    "headline": "GTA Online",
    "subtitle": "Geschenke zum Mondfest",
    "content": "Feiere das Mondfest, indem du bis 18.µSeptember GTA Online spielst und drei Herbstpullover in Schwarz, Weiß und Rot von der sagenumwobenen Streetwear-Marke YETI erhältst, die entworfen wurden, um dieses Fest des Zusammenkommens und der Dankbarkeit angemessen zu begehen.",
    "url": "",
    "image": {
        "path": "sc/news/056dd7116e874854b72aa5b8/262272_GTAO_417_MoonFestival_FINAL_BigFeed_R01_de_de.dds",
        "filesize": 262272
    }
}