{
    "types": [
        "transition"
    ],
    "date": 1722007828,
    "title": "GTA Online",
    "headline": "GTA Online",
    "subtitle": "Podkręć tempo przy dostawie pizzy",
    "content": "Wskocz na skuter Pizza Boy i śmigaj po całym Los Santos, rozwożąc pizzę do głodnych klientów w zamian za gotówkę. Jeśli dostarczysz jedzenie, zanim wystygnie, otrzymasz premię. Dostarcz 50 pizz, żeby odblokować nagrodę specjalną.<br /><br />Odwiedź punkt Pizza This…, aby rozpocząć.",
    "url": "",
    "image": {
        "path": "sc/news/4c938ca5e5da44c0b000dc78/262272_GTAO_406_PizzaDelivery_FINAL_BigFeed.dds",
        "filesize": 262272
    }
}