{
    "types": [
        "transition"
    ],
    "date": 1629998014,
    "title": "",
    "headline": "GTA Online",
    "subtitle": "Discounts",
    "content": "Afraid of showing up to the Car Meet in a rust bucket? Spice up your collection by adding a Vapid Dominator GTT for 30% off, as well as 40% off a selection of vehicles. Meanwhile, all Bunkers are half off, while their Upgrades are on sale for 40% off for the next week.<br /><br />- Vapid Dominator GTT – 30% off<br />- Bravado Half-Track – 40% off<br />- Dewbauchee Specter – 30% off<br />- All Bunkers – 50% off<br /><br />And more! Check out the Rockstar Newswire for more details.",
    "url": "",
    "image": {
        "path": "sc/news/984c58fe0b7a4c97b7dacbe3/352384_GTA0263_Discounts_FINAL_BigFeedcopy.dds",
        "filesize": 352384
    }
}