{
    "types": [
        "transition"
    ],
    "date": 1689949465,
    "title": "",
    "headline": "GTA Online",
    "subtitle": "Inductor",
    "content": "Want to come face-to-face with San Andreas’s deadliest mountain trails? Meet the Inductor. Its technologically advanced motor means less legwork all the way up to the peak, and its streamlined design means unstoppable force all the way down to the ER. <br /><br />Now available from Pedal & Metal. Wear a helmet.",
    "url": "",
    "image": {
        "path": "sc/news/1bb4c23669f6450a9a6fba4b/262272_GTAO_358_Coillnductor_FINAL_BigFeed.dds",
        "filesize": 262272
    }
}