{
    "types": [
        "transition"
    ],
    "date": 1751015846,
    "title": "GTA Online",
    "headline": "GTA Online",
    "subtitle": "2xµGTA$ und RP für Geldwäschemissionen für Higgins Helitours",
    "content": "Nutze deine Flotte von Rundflughubschraubern, um in den Geldwäschemissionen für Higgins Helitours verlorene Fracht zu bergen. Dabei werden mutigen Piloten bis zum 2.µJuli doppelte Belohnungen ausgezahltµ– und Mitgliedern bei GTA+ sogar vierfache Belohnungen.<br /><br />Spieler, die in der Luftfahrt-Tourismusbranche abheben möchten, können dies tun, nachdem sie die Hands-On-Waschanlage bei Maze Bank Foreclosures gekauft haben.",
    "url": "",
    "image": {
        "path": "sc/news/7550a3a13b8a4984bc7ae05c/262272_GTAO_455_S25TU_HigginsHelitours_FINAL_BigFeed_R02_Deliv.dds",
        "filesize": 262272
    }
}