{
    "types": [
        "transition"
    ],
    "date": 1608039623,
    "title": "",
    "headline": "GTA Online",
    "subtitle": "The Cayo Perico Heist",
    "content": "Ограбить крупнейший банк в стране? Уже грабили. Обчистить хранилище казино? Тоже избитая тема. Проникнуть на хорошо охраняемый тропический остров, которым заправляет жестокий наркобарон Эль Рубио? Вот это другой разговор.<br /><br />На смену огням Лос-Сантоса придут пески Кайо-Перико, где у вас будет шанс сорвать действительно баснословный куш. Все, что требуется, – выйти на нужного человека, и такой человек ждет вас в ВИП-зоне нового модного клуба Music Locker.",
    "url": "",
    "image": {
        "path": "sc/news/02ed1ff060174a6f8d2058d6/262272_TheCayoPericoHeist.dds",
        "filesize": 262272
    }
}