{
    "types": [
        "transition"
    ],
    "date": 1770391018,
    "title": "GTA Online",
    "headline": "GTA Online",
    "subtitle": "Vista o Onesie Namorados",
    "content": "Ao vestir o Onesie Namorados, você e sua cara-metade podem combinar lindamente em tons cor-de-rosa. Entre no GTA Online até 18 de fevereiro para receber esse onesie dos apaixonados.<br /><br />Não importa se você está desfrutando da glória de um primeiro encontro perfeito ou tentando esquecer uma rapidinha lamentável, tire o gosto que ficou da experiência com Champagne grátis em todas as Boates nesta e na próxima semana.",
    "url": "",
    "image": {
        "path": "sc/news/141d1acb96e24b22884887a1/262272_GTAO_485_ValentinesDayClothingCarousel_Onesie_FINAL_BigFeed_Deliv.dds",
        "filesize": 262272
    }
}