{"types":["transition"],"date":1518532405,"title":"","headline":"GTA Online","subtitle":"Hustler","content":"Esistono due tipi di persone. Il primo resta confuso di fronte alla Vapid Hustler e cerca di dare un senso alla combinazione di eleganza da coupé degli anni 30 e ferocia da muscle car. Il secondo ci salta subito sopra e aggredisce la strada con il pedale a tavoletta, capendo che i suoi sogni si sono avverati. E tu quale dei due vuoi essere?","url":"","image":{"path":"sc/news/DH_Vapid_Hustler/524416_BIGFEED_2017_1212_V01_E_512x1024_Hustler.dds","filesize":524416},"style":"gta"}