{"types":["transition"],"date":1676637979,"title":"","headline":"GTA Online","subtitle":"ГРОЗА НАРКОБАЗ","content":"Оставаться королем свободного рынка – дело непростое. Сделайте Джеральду одолжение и расправьтесь с его конкурентами, устраивая налеты на наркобазы по всему Лос-Сантосу. Каждый день вас ждет новая цель и новая возможность положить в карман солидную сумму и добыть сырье для ваших предприятий.","url":"","image":{"path":"sc/news/f0a38c642a464bcaaf1c1c7d/524416_GTAO337_NewDailyFreemodeEvents_FINAL_BigFeed.dds","filesize":524416}}