{"types":["transition"],"date":1679049787,"title":"","headline":"GTA Online","subtitle":"Erlebe The First Dose","content":"Erlebe jetzt The First Dose, falls du den Sprung bislang noch nicht gewagt hast.<br /><br />Mach dich direkt auf nach Blaine County und nimm den Anruf von Ron Jakowski entgegen, um mit dem Eröffnungskapitel der Saga zu beginnen.<br /><br />Im Verlauf der Story erhältst du Zugriff auf den Freakshop als Operationsbasis. Du richtest ein mobiles Drogenlabor ein und vertreibst dein Produkt in ganz Los Santos, während du gleichzeitig das Geschäft deiner Konkurrenten sabotierst.","url":"","image":{"path":"sc/news/84823a5c24e14fbaaae641f1/262272_GTAO_LSDW_FINAL_BigFeed_copy.dds","filesize":262272}}