{"types":["transition"],"date":1539096537,"title":"","headline":"GTA Online","subtitle":"Karin Futo, Bollokan Prairie, Imponte Ruiner","content":"Drei weitere ikonische Autos haben diese Woche ihren Weg in die Ausstellungsräume von Los Santos gefunden. Ja, es ist endlich Zeit, einen Imponte Ruiner zu besitzen, der nicht wie der kahlwerdende Rohstoffhändler riecht, von dem du ihn gestohlen hast.<br /><br />Und nicht nur für diese Drei stehen neue Designs zur Verfügung, sondern auch für den Maibatsu Penumbra, den Declasse Mamba und den Invetero Coquette Classic.","url":"","image":{"path":"sc/news/f2c_AH_Futo/349672_FUTO_PRAIRIE_RUINER.dds","filesize":349672},"style":"gta"}