{"types":["transition"],"date":1686326174,"title":"Clube de Carros Vinewood","headline":"Clube de Carros Vinewood","subtitle":"A mais nova adição ao GTA+ chega em 13 de junho","content":"Apresentamos o Clube de Carros Vinewood — um destino apenas para membros e oferecimento inaugural do Clube Vinewood —, o novo serviço premium em Los Santos para membros do GTA+ que chega em 13 de junho.<br /><br />Os membros do Clube Vinewood terão acesso a um estoque seleto de veículos distintos para fazer test drive, solicitar no Modo Livre e comprar com desconto exclusivo de 20% ou mais.<br /><br />Saiba mais no Boletim da Rockstar.","url":"","image":{"path":"sc/news/522dc257b6f54b3b8411c50c/262272_GTAO_354_VinewoodAnnounce_Lead_FINAL_BigFeed.dds","filesize":262272}}