{
    "types": [
        "standalone"
    ],
    "date": 1753955109,
    "title": "Afilie-se ao GTA+",
    "headline": "Afilie-se ao GTA+",
    "subtitle": "Ganhe 4x GTA$ e RP em Vai ou Racha (Cayo Perico)",
    "content": "Junte-se à afiliação premium do GTA Online esta semana para receber 4x recompensas no novo Vai ou Racha (Cayo Perico) até 6 de agosto.<br /><br />O GTA+ é renovado automaticamente todo mês e pode ser cancelado a qualquer momento. Saiba mais em rsg.ms/gtaplus.",
    "url": "class=uiGoToOnlineMode mode=SRCM_FREE argtype=SRCA_STORE_PRODUCT arg=GTAOPlus",
    "image": {
        "path": "sc/news/d168bc1d4fd6401db5d0f340/262272_GTAO_460_Lead_CayoPericoMotorWars_FINAL_BigFeed_R01_Deliv.dds",
        "filesize": 262272
    }
}