{
    "types": [
        "transition"
    ],
    "date": 1631210252,
    "title": "",
    "headline": "GTA Online",
    "subtitle": "W tym tygodniu na podium: Truffade Adder",
    "content": "Wpadnij w tym tygodniu do lobby Diamond Casino & Resort, żeby zakręcić kołem fortuny i wygrać GTA$, RP, ubrania, przekąski, tajemnicze nagrody i nie tylko. W tym tygodniu na podium czeka Truffade Adder, czyli paliwożerny hipersamochód, który budzi strach w sercach protestujących ekologów na całym świecie.",
    "url": "",
    "image": {
        "path": "sc/news/4a53664725614397a70f3467/349672_podium_wheel1.dds",
        "filesize": 349672
    }
}