{
    "types": [
        "transition"
    ],
    "date": 1617295732,
    "title": "",
    "headline": "GTA Online",
    "subtitle": "ガレージの割引など",
    "content": "期間中「GTAオンライン」のプレイヤーは、ガレージや格納庫などの不動産が40％オフになるなど、色々な割引を受けられます。<br /><br />格納庫の追加設備&改装µ-µ40％オフ<br />ナガサキµアウトローµ-µ40％オフ<br />カリンµサルタンレトロµ-µ40％オフ<br />コケットD10µ-µ40％オフ<br /><br />他にもいろいろ！詳細はロックスターNewswireをご覧ください。",
    "url": "",
    "image": {
        "path": "sc/news/da157be39b8e43aea9f18f4b/262272_FINAL_Karin_Sultan_Classic_Big_Feed_Only_512x1024.dds",
        "filesize": 262272
    }
}