{
    "types": [
        "transition"
    ],
    "date": 1750244711,
    "title": "GTA Online: Money Fronts",
    "headline": "GTA Online: Money Fronts",
    "subtitle": "Verbesserungen der Spielerfahrung",
    "content": "GTA Online: Money Fronts führt eine Reihe von Verbesserungen ein, darunter die Möglichkeit, 50 weitere Fahrzeuge mit dem Lenkraketen-Störsender auszustatten, das Überspringen mehrerer Zwischensequenzen bei Missionswiederholungen und die Verdopplung aller Bezugsquellen von Arenapunkten. <br /><br />Zusätzliche Verbesserungen umfassen die Verzögerung des globalen Signaltimers für Verkaufsmissionen in öffentlichen Sitzungen und die Deaktivierung des Boxville-Lieferwagens aus Biker-Verkaufsmissionen.",
    "url": "",
    "image": {
        "path": "sc/news/1820df124bfd468f9fe7203f/262272_GTAO_STU25_MissileLockOnJammer_FINAL_BigFeed_Deliv.dds",
        "filesize": 262272
    }
}