{
    "types": [
        "transition"
    ],
    "date": 1629998830,
    "title": "",
    "headline": "GTA Online",
    "subtitle": "Karin Sultan RS Classic",
    "content": "Представьте, что вы на ралли: до финиша – полпути, стресс зашкаливает. Какой автомобиль вы предпочли бы в такой ситуации? Надежный, безопасный и легко управляемый? Или безрассудный, своенравный и набитый под завязку модификациями? А что получится, если соединить эти качества в одной модели? Познакомьтесь с Karin Sultan RS Classic. Эта машина продается в каталоге SSASA.",
    "url": "",
    "image": {
        "path": "sc/news/89c5043655364fe0a8de6ba3/262272_GTAO263_LeadAsset_SultanClassic_FINAL_BigFeed.dds",
        "filesize": 262272
    }
}