{"types":["transition"],"date":1673002612,"title":"","headline":"GTA Online","subtitle":"GTA$ e RP doppi in tutte le missioni di Prima dose di Los Santos Drug Wars","content":"I Fooliganz stanno creando scompiglio a Los Santos, con Dax e il suo gruppo di disadattati che stanno seminando una scia di caos psichedelico. Questa settimana, fornisci supporto, elimina le bande rivali e unisciti alla troupe nelle missioni di Prima dose per mettere le mani su ricompense doppie.","url":"","image":{"path":"sc/news/9191b595391941d2a94df4d1/262272_GTAO_LSDW_FINAL_BigFeed_copy.dds","filesize":262272}}