{
    "types": [
        "transition"
    ],
    "date": 1729249691,
    "title": "GTA Online",
    "headline": "GTA Online",
    "subtitle": "2x więcej GTA$ i RP za Oprawcę",
    "content": "Przydybaj siedem Ofiar jako Oprawca uzbrojony w strzelbę. Po trzech minutach dynamika rywalizacji ulega zmianie – ofiary otrzymują strzelby i stają się łowcami. Obie strony konfliktu otrzymują podwójne nagrody przez cały tydzień (poczwórne w przypadku członków GTA+).<br /><br />Dołącz do akcji, wchodząc do Serii wyróżnionej na Legion Square lub przechodząc w tryby adwersarza z poziomu menu pauzy.<br />",
    "url": "",
    "image": {
        "path": "sc/news/1647dac0685b46a6ae22283a/262272_GTAO271_Slashers_FINAL_BigFeed.dds",
        "filesize": 262272
    }
}