{
    "types": [
        "transition"
    ],
    "date": 1728051529,
    "title": "GTA 온라인",
    "headline": "GTA 온라인",
    "subtitle": "로스 산토스에 찾아온 할로윈",
    "content": "오늘부터 로스 산토스 남부의 거리 안팎에서 한 달간 할로윈 기념 이벤트가 시작되며, 완전히 다른 종류의 스릴 넘치는 만남으로 끝을 맞이합니다.<br /><br />이번 주에 돌아오는 사형수에서 적을 처치하며 으스스한 분위기를 만끽하고, 로스 산토스 전역의 상점에서 시즌 한정 할로윈 가면, 페이스 페인팅, 자동차 경적, 보블헤드를 만나보세요.<br /><br />그리고 다음 주에는 양크턴 북부의 범죄 현장으로 돌아가 새로운 커뮤니티 도전에서 몰려오는 언데드 무리를 물리치세요. 기간 한정으로 플레이할 수 있습니다.<br />",
    "url": "",
    "image": {
        "path": "sc/news/22aca97ed570456faea41142/262272_GTAO_420_Halloween_FINAL_BigFeed.dds",
        "filesize": 262272
    }
}