{
    "types": [
        "standalone"
    ],
    "date": 1730802420,
    "title": "",
    "headline": "GTA Online",
    "subtitle": "La statua di pantera ritorna",
    "content": "La sfuggente statua di pantera, il sogno di ogni contrabbandiere con il suo bagliore dorato e le brillanti sfere blu, è tornata. I ladri possono mettere nel mirino la statua di pantera come bersaglio principale del loro primo colpo in The Cayo Perico Heist tra il 7 e il 13 novembre.",
    "url": "",
    "image": {
        "path": "sc/news/f845fb573808419a9b28ed6e/262272_GTAO_322_PantherStatue_FINAL_BigFeed_NoLogo.dds",
        "filesize": 262272
    }
}