{
    "types": [
        "transition"
    ],
    "date": 1684500971,
    "title": "",
    "headline": "GTA Online",
    "subtitle": "Bonus per Los Santos Tuners e l'autofficina",
    "content": "I bonus per Los Santos Tuners e l’autofficina ti danno una marcia in più in GTA Online.<br /><br />Guadagna RP doppi partecipando alle gare clandestine o agli inseguimenti e, questa settimana, ottieni ricompense triple nei lavori per i clienti dell'autofficina e nei contratti.<br /><br />In più, approfitta di una serie di sconti sulle auto e altro ancora.<br />",
    "url": "",
    "image": {
        "path": "sc/news/7497c3e53f0641dca643cd66/262272_GTAO_350_LeadAsset_FINAL_BigFeedcopy.dds",
        "filesize": 262272
    }
}